README
setup.py
attrcheck.egg-info/PKG-INFO
attrcheck.egg-info/SOURCES.txt
attrcheck.egg-info/dependency_links.txt
attrcheck.egg-info/top_level.txt
src/__init__.py
src/attrcheck.py
src/test_attrcheck.py