Metadata-Version: 1.0
Name: attrcheck
Version: 0.1.2
Summary: A simple attribution checker implemented as a decorator
Home-page: https://github.com/jnamika/attrcheck
Author: Jun Namikawa
Author-email: jnamika@gmail.com
License: ISC License (ISCL)
Keywords: argument check hasattr decorator
Platform: UNKNOWN
Classifier: Development Status :: 3 - Alpha
Classifier: Intended Audience :: Developers
Classifier: License :: OSI Approved :: ISC License (ISCL)
Classifier: Operating System :: OS Independent
Classifier: Programming Language :: Python
Classifier: Topic :: Software Development :: Libraries :: Python Modules
